likeness/__init__.py
likeness/discount.py
likeness/ignore.py
likeness/likeness.py
likeness/likeness_mixin.py
likeness/py.typed
likeness-1.0.2.dist-info/METADATA
likeness-1.0.2.dist-info/WHEEL
likeness-1.0.2.dist-info/RECORD
